seqlabel/__init__.py
seqlabel/core.py
seqlabel/entity_filters.py
seqlabel/matchers.py
seqlabel/serializers.py
seqlabel-0.2.4.dist-info/LICENSE
seqlabel-0.2.4.dist-info/WHEEL
seqlabel-0.2.4.dist-info/METADATA
seqlabel-0.2.4.dist-info/RECORD
