Metadata-Version: 2.1
Name: seqlabel
Version: 0.2.4
Summary: Rule-based Text Labeling Framework Aiming at Flexibility
Home-page: https://github.com/tech-sketch/seqlabel
License: MIT
Author: Yasufumi Taniguchi
Author-email: yasufumi.taniguchi@gmail.com
Requires-Python: >=3.7,<4.0
Classifier: License :: OSI Approved :: MIT License
Classifier: Programming Language :: Python :: 3
Classifier: Programming Language :: Python :: 3.7
Classifier: Programming Language :: Python :: 3.8
Classifier: Programming Language :: Python :: 3.9
Requires-Dist: pyahocorasick (>=1.4.2,<2.0.0)
Requires-Dist: pytokenizations (>=0.8.4,<0.9.0)
Project-URL: Repository, https://github.com/tech-sketch/seqlabel
